Metadata-Version: 2.1
Name: nflow
Version: 0.1.0
Summary: A Python SDK for nFlow client pipelines.
Home-page: https://example.com
Author: Your Name
Author-email: youremail@example.com
Classifier: Programming Language :: Python :: 3
Classifier: License :: OSI Approved :: MIT License
Classifier: Operating System :: OS Independent
Requires-Python: >=3.7
License-File: LICENSE
Requires-Dist: tqdm>=4.0
